[
  {
    "id": 1,
    "title": { "first": "A Night of", "second": "Experiences" },
    "image": "/custom-content/patch.mov",
    "sub": "Design",
    "video": true
  },
  {
    "id": 2,
    "title": { "first": "Worldly & Elegant", "second": "Cocktails" },
    "image": "/img/portfolio/full/2.jpg",
    "sub": "Design",
    "video": false
  },
  {
    "id": 3,
    "title": { "first": "House Beats &", "second": "Chic Music" },
    "image": "/img/portfolio/full/3.jpg",
    "sub": "Design",
    "video": false
  },
  {
    "id": 4,
    "title": { "first": "Memorable Events", "second": "In the City" },
    "image": "/img/portfolio/full/3.jpg",
    "sub": "Design",
    "video": false
  }
]
